pdm_plugin_torch-23.4.0.dist-info/METADATA
pdm_plugin_torch-23.4.0.dist-info/WHEEL
pdm_plugin_torch-23.4.0.dist-info/entry_points.txt
pdm_plugin_torch-23.4.0.dist-info/licenses/LICENSE-APACHE
pdm_plugin_torch-23.4.0.dist-info/licenses/LICENSE-MIT
pdm_plugin_torch/__init__.py
pdm_plugin_torch/config.py
pdm_plugin_torch/main.py
pdm_plugin_torch-23.4.0.dist-info/RECORD
