Metadata-Version: 2.1
Name: pdm-plugin-torch
Version: 23.4.0
Summary: A plugin to help installing torch versions
Author-Email: Embark Studios <python@embark-studios.com>
License: MIT
Project-URL: Repository, https://github.com/EmbarkStudios/pdm-plugin-torch
Requires-Python: >=3.8
